{"time":{"start":"2022-04-08T16:57:00.000Z","end":"2022-04-08T16:58:00.000Z"},"OPM":71,"total_sale_volume":"1,648.06","average_transaction_size":"23.21","rate_of_return":"0.00"}
{"time":{"start":"2022-04-10T22:31:00.000Z","end":"2022-04-10T22:32:00.000Z"},"OPM":51,"total_sale_volume":"1,412.21","average_transaction_size":"27.69","rate_of_return":"0.06"}
{"time":{"start":"2022-04-12T11:36:00.000Z","end":"2022-04-12T11:37:00.000Z"},"OPM":22,"total_sale_volume":"436.59","average_transaction_size":"19.84","rate_of_return":"0.00"}
{"time":{"start":"2022-04-13T05:10:00.000Z","end":"2022-04-13T05:11:00.000Z"},"OPM":14,"total_sale_volume":"250.95","average_transaction_size":"17.93","rate_of_return":"0.00"}
{"time":{"start":"2022-04-09T18:03:00.000Z","end":"2022-04-09T18:04:00.000Z"},"OPM":24,"total_sale_volume":"1,722.58","average_transaction_size":"71.77","rate_of_return":"0.08"}
{"time":{"start":"2022-04-11T22:20:00.000Z","end":"2022-04-11T22:21:00.000Z"},"OPM":40,"total_sale_volume":"805.95","average_transaction_size":"20.15","rate_of_return":"0.00"}
{"time":{"start":"2022-04-09T17:52:00.000Z","end":"2022-04-09T17:53:00.000Z"},"OPM":55,"total_sale_volume":"627.50","average_transaction_size":"11.41","rate_of_return":"0.00"}
{"time":{"start":"2022-04-11T08:41:00.000Z","end":"2022-04-11T08:42:00.000Z"},"OPM":7,"total_sale_volume":"141.09","average_transaction_size":"20.16","rate_of_return":"0.00"}
{"time":{"start":"2022-04-10T10:57:00.000Z","end":"2022-04-10T10:58:00.000Z"},"OPM":46,"total_sale_volume":"742.04","average_transaction_size":"16.13","rate_of_return":"0.00"}
{"time":{"start":"2022-04-09T16:41:00.000Z","end":"2022-04-09T16:42:00.000Z"},"OPM":41,"total_sale_volume":"681.71","average_transaction_size":"16.63","rate_of_return":"0.00"}
{"time":{"start":"2022-04-09T09:08:00.000Z","end":"2022-04-09T09:09:00.000Z"},"OPM":15,"total_sale_volume":"321.47","average_transaction_size":"21.43","rate_of_return":"0.13"}
{"time":{"start":"2022-04-09T21:50:00.000Z","end":"2022-04-09T21:51:00.000Z"},"OPM":29,"total_sale_volume":"422.99","average_transaction_size":"14.59","rate_of_return":"0.00"}
{"time":{"start":"2022-04-08T12:04:00.000Z","end":"2022-04-08T12:05:00.000Z"},"OPM":29,"total_sale_volume":"388.97","average_transaction_size":"13.41","rate_of_return":"0.34"}
{"time":{"start":"2022-04-10T04:34:00.000Z","end":"2022-04-10T04:35:00.000Z"},"OPM":19,"total_sale_volume":"308.78","average_transaction_size":"16.25","rate_of_return":"0.26"}
{"time":{"start":"2022-04-11T12:39:00.000Z","end":"2022-04-11T12:40:00.000Z"},"OPM":48,"total_sale_volume":"677.34","average_transaction_size":"14.11","rate_of_return":"0.00"}
{"time":{"start":"2022-04-13T05:48:00.000Z","end":"2022-04-13T05:49:00.000Z"},"OPM":38,"total_sale_volume":"390.21","average_transaction_size":"10.27","rate_of_return":"0.13"}
{"time":{"start":"2022-04-11T07:21:00.000Z","end":"2022-04-11T07:22:00.000Z"},"OPM":32,"total_sale_volume":"751.48","average_transaction_size":"23.48","rate_of_return":"0.03"}
{"time":{"start":"2022-04-08T08:18:00.000Z","end":"2022-04-08T08:19:00.000Z"},"OPM":31,"total_sale_volume":"331.75","average_transaction_size":"10.70","rate_of_return":"0.03"}
{"time":{"start":"2022-04-13T04:28:00.000Z","end":"2022-04-13T04:29:00.000Z"},"OPM":27,"total_sale_volume":"804.33","average_transaction_size":"29.79","rate_of_return":"0.07"}
{"time":{"start":"2022-04-11T15:17:00.000Z","end":"2022-04-11T15:18:00.000Z"},"OPM":47,"total_sale_volume":"1,581.54","average_transaction_size":"33.65","rate_of_return":"0.17"}
{"time":{"start":"2022-04-12T12:17:00.000Z","end":"2022-04-12T12:18:00.000Z"},"OPM":25,"total_sale_volume":"343.68","average_transaction_size":"13.75","rate_of_return":"0.20"}
{"time":{"start":"2022-04-10T12:29:00.000Z","end":"2022-04-10T12:30:00.000Z"},"OPM":18,"total_sale_volume":"371.94","average_transaction_size":"20.66","rate_of_return":"0.00"}
{"time":{"start":"2022-04-12T01:36:00.000Z","end":"2022-04-12T01:37:00.000Z"},"OPM":24,"total_sale_volume":"403.50","average_transaction_size":"16.81","rate_of_return":"0.00"}
{"time":{"start":"2022-04-10T08:54:00.000Z","end":"2022-04-10T08:55:00.000Z"},"OPM":17,"total_sale_volume":"168.75","average_transaction_size":"9.93","rate_of_return":"0.24"}
{"time":{"start":"2022-04-11T12:12:00.000Z","end":"2022-04-11T12:13:00.000Z"},"OPM":25,"total_sale_volume":"430.21","average_transaction_size":"17.21","rate_of_return":"0.36"}
{"time":{"start":"2022-04-09T08:34:00.000Z","end":"2022-04-09T08:35:00.000Z"},"OPM":34,"total_sale_volume":"351.16","average_transaction_size":"10.33","rate_of_return":"0.00"}
{"time":{"start":"2022-04-11T00:49:00.000Z","end":"2022-04-11T00:50:00.000Z"},"OPM":26,"total_sale_volume":"959.55","average_transaction_size":"36.91","rate_of_return":"0.00"}
{"time":{"start":"2022-04-11T11:05:00.000Z","end":"2022-04-11T11:06:00.000Z"},"OPM":24,"total_sale_volume":"268.19","average_transaction_size":"11.17","rate_of_return":"0.12"}
{"time":{"start":"2022-04-08T06:22:00.000Z","end":"2022-04-08T06:23:00.000Z"},"OPM":28,"total_sale_volume":"337.67","average_transaction_size":"12.06","rate_of_return":"0.00"}
{"time":{"start":"2022-04-08T23:58:00.000Z","end":"2022-04-08T23:59:00.000Z"},"OPM":30,"total_sale_volume":"709.69","average_transaction_size":"23.66","rate_of_return":"0.07"}
{"time":{"start":"2022-04-07T16:37:00.000Z","end":"2022-04-07T16:38:00.000Z"},"OPM":33,"total_sale_volume":"1,483.11","average_transaction_size":"44.94","rate_of_return":"0.06"}
{"time":{"start":"2022-04-08T03:43:00.000Z","end":"2022-04-08T03:44:00.000Z"},"OPM":28,"total_sale_volume":"932.67","average_transaction_size":"33.31","rate_of_return":"0.07"}
{"time":{"start":"2022-04-10T12:03:00.000Z","end":"2022-04-10T12:04:00.000Z"},"OPM":32,"total_sale_volume":"756.50","average_transaction_size":"23.64","rate_of_return":"0.19"}
{"time":{"start":"2022-04-10T23:09:00.000Z","end":"2022-04-10T23:10:00.000Z"},"OPM":30,"total_sale_volume":"715.53","average_transaction_size":"23.85","rate_of_return":"0.00"}
{"time":{"start":"2022-04-10T08:34:00.000Z","end":"2022-04-10T08:35:00.000Z"},"OPM":25,"total_sale_volume":"462.81","average_transaction_size":"18.51","rate_of_return":"0.00"}
{"time":{"start":"2022-04-12T18:57:00.000Z","end":"2022-04-12T18:58:00.000Z"},"OPM":43,"total_sale_volume":"528.72","average_transaction_size":"12.30","rate_of_return":"0.00"}
{"time":{"start":"2022-04-09T22:55:00.000Z","end":"2022-04-09T22:56:00.000Z"},"OPM":16,"total_sale_volume":"965.16","average_transaction_size":"60.32","rate_of_return":"0.19"}
{"time":{"start":"2022-04-13T00:46:00.000Z","end":"2022-04-13T00:47:00.000Z"},"OPM":47,"total_sale_volume":"826.19","average_transaction_size":"17.58","rate_of_return":"0.00"}
